.gitignore
MANIFEST.in
README.txt
bootstrap.py
buildout.cfg
setup.py
collective/__init__.py
collective.openidselector.egg-info/PKG-INFO
collective.openidselector.egg-info/SOURCES.txt
collective.openidselector.egg-info/dependency_links.txt
collective.openidselector.egg-info/entry_points.txt
collective.openidselector.egg-info/namespace_packages.txt
collective.openidselector.egg-info/not-zip-safe
collective.openidselector.egg-info/requires.txt
collective.openidselector.egg-info/top_level.txt
collective/openidselector/__init__.py
collective/openidselector/configure.zcml
collective/openidselector/includes.pt
collective/openidselector/resources/openid-providers.js
collective/openidselector/resources/openid-wrapper.js
collective/openidselector/resources/openid-selector/README.txt
collective/openidselector/resources/openid-selector/demo-mootools.html
collective/openidselector/resources/openid-selector/demo-prototype.html
collective/openidselector/resources/openid-selector/demo-ru.html
collective/openidselector/resources/openid-selector/demo-uk.html
collective/openidselector/resources/openid-selector/demo.html
collective/openidselector/resources/openid-selector/generate-sprite.js
collective/openidselector/resources/openid-selector/generate-sprite.rb
collective/openidselector/resources/openid-selector/generate-sprite.sh
collective/openidselector/resources/openid-selector/remcomments.sed
collective/openidselector/resources/openid-selector/css/openid-shadow.css
collective/openidselector/resources/openid-selector/css/openid.css
collective/openidselector/resources/openid-selector/images/openid-inputicon.gif
collective/openidselector/resources/openid-selector/images/openid-providers-en.png
collective/openidselector/resources/openid-selector/images/openid-providers-ru.png
collective/openidselector/resources/openid-selector/images.large/aol.gif
collective/openidselector/resources/openid-selector/images.large/facebook.gif
collective/openidselector/resources/openid-selector/images.large/fedora.gif
collective/openidselector/resources/openid-selector/images.large/google.gif
collective/openidselector/resources/openid-selector/images.large/mailru.gif
collective/openidselector/resources/openid-selector/images.large/myopenid.gif
collective/openidselector/resources/openid-selector/images.large/openid.gif
collective/openidselector/resources/openid-selector/images.large/rambler.gif
