Metadata-Version: 1.0
Name: collective.openidselector
Version: 0.1
Summary: Integration of openid-selector for plone
Home-page: https://github.com/inigoconsulting/collective.openidselector
Author: UNKNOWN
Author-email: UNKNOWN
License: BSD
Platform: UNKNOWN
Classifier: Programming Language :: Python
